imagination_to_real/image_maker/__init__.py
imagination_to_real/image_maker/render_node.py
imagination_to_real/image_maker/utils.py
imagination_to_real/image_maker/scripts/demo_three_mask_workflow.py
imagination_to_real/image_maker/workflows/__init__.py
imagination_to_real/image_maker/workflows/three_mask_workflow.py
imagination_to_real/lucidsim/__init__.py
imagination_to_real/lucidsim/cfgs/parkour.py
imagination_to_real/lucidsim/model/__init__.py
imagination_to_real/lucidsim/model/utils.py
imagination_to_real/lucidsim/model/modules/__init__.py
imagination_to_real/lucidsim/model/modules/actor_critic.py
imagination_to_real/lucidsim/model/modules/depth_backbone.py
imagination_to_real/lucidsim/model/modules/estimator.py
imagination_to_real/lucidsim/model/modules/parkour_actor.py
imagination_to_real/lucidsim/scripts/play.py
imagination_to_real/lucidsim/scripts/play_three_mask_workflow.py
imagination_to_real/lucidsim/tasks/__init__.py
imagination_to_real/lucidsim/tasks/gaps.py
imagination_to_real/lucidsim/tasks/hurdle.py
imagination_to_real/lucidsim/tasks/parkour.py
imagination_to_real/lucidsim/tasks/stairs_v1.py
imagination_to_real/lucidsim/tasks/stairs_v2.py
imagination_to_real/lucidsim/tasks/base/__init__.py
imagination_to_real/lucidsim/tasks/base/go1_base.py
imagination_to_real/lucidsim/traj_samplers/__init__.py
imagination_to_real/lucidsim/traj_samplers/unroll_flow_stream.py
imagination_to_real/lucidsim/utils/depth_util.py
imagination_to_real/lucidsim/utils/optical_flow.py
imagination_to_real/lucidsim/utils/tf_utils.py
imagination_to_real/lucidsim/utils/transform_utils.py
imagination_to_real/lucidsim/utils/utils.py
imagination_to_real/lucidsim/wrappers/depth_midas_render_wrapper.py
imagination_to_real/lucidsim/wrappers/history_wrapper.py
imagination_to_real/lucidsim/wrappers/lucid_env.py
imagination_to_real/lucidsim/wrappers/optical_flow_wrapper.py
imagination_to_real/lucidsim/wrappers/render_rgb_wrapper.py
imagination_to_real/lucidsim/wrappers/reset_wrapper.py
imagination_to_real-0.1.0.dist-info/LICENSE
imagination_to_real-0.1.0.dist-info/METADATA
imagination_to_real-0.1.0.dist-info/WHEEL
imagination_to_real-0.1.0.dist-info/top_level.txt
imagination_to_real-0.1.0.dist-info/RECORD
