Metadata-Version: 2.1
Name: imagination_to_real
Version: 0.1.0
Summary: Train your robot to do whatever you want using Generative AI
Author-email: SmilingRobo <support@smilingrobo.com>
License: Apache License
Project-URL: Homepage, https://www.smilingrobo.com/
Project-URL: Source, https://github.com/SmilingRobo/imagination-to-real
License-File: LICENSE
Requires-Dist: numpy ==1.26.3
Requires-Dist: params-proto
Requires-Dist: dm-control ==1.0.17
Requires-Dist: matplotlib ==3.8.2
Requires-Dist: torchtyping ==0.1.4
Requires-Dist: opencv-python ==4.9.0.80
Requires-Dist: mujoco ==3.1.3
